keeleastrolab/__init__.py
keeleastrolab/astrometry_index_files.csv
keeleastrolab/bright_star_cat.csv
keeleastrolab/camera_database.csv
keeleastrolab/raw2fits.py
keeleastrolab/stackfits.py
keeleastrolab/tools.py
keeleastrolab-0.1.0.dist-info/LICENSE
keeleastrolab-0.1.0.dist-info/METADATA
keeleastrolab-0.1.0.dist-info/WHEEL
keeleastrolab-0.1.0.dist-info/entry_points.txt
keeleastrolab-0.1.0.dist-info/top_level.txt
keeleastrolab-0.1.0.dist-info/RECORD
