Metadata-Version: 2.1
Name: keeleastrolab
Version: 0.1.0
Summary: Convenience functions for Keele astrophysics lab students
Author-email: Pierre Maxted <p.maxted@keele.ac.uk>
Project-URL: Homepage, https://github.com/pmaxted/keeleastrolab
Project-URL: Issues, https://github.com/pmaxted/keeleastrolab/issues
Classifier: Programming Language :: Python :: 3
Classifier: License :: OSI Approved :: MIT License
Classifier: Operating System :: OS Independent
Requires-Python: >=3.8
License-File: LICENSE
Requires-Dist: rawpy
Requires-Dist: exiv2
Requires-Dist: astropy
Requires-Dist: astrometry
Requires-Dist: photutils
